dclab/__init__.py
dclab/_version.py
dclab/cached.py
dclab/downsampling.cp310-win_amd64.pyd
dclab/downsampling.pyx
dclab/http_utils.py
dclab/kde_contours.py
dclab/kde_methods.py
dclab/polygon_filter.py
dclab/statistics.py
dclab/util.py
dclab/warn.py
dclab/cli/__init__.py
dclab/cli/common.py
dclab/cli/task_compress.py
dclab/cli/task_condense.py
dclab/cli/task_join.py
dclab/cli/task_repack.py
dclab/cli/task_split.py
dclab/cli/task_tdms2rtdc.py
dclab/cli/task_verify_dataset.py
dclab/definitions/__init__.py
dclab/definitions/feat_const.py
dclab/definitions/feat_logic.py
dclab/definitions/meta_const.py
dclab/definitions/meta_logic.py
dclab/definitions/meta_parse.py
dclab/external/__init__.py
dclab/external/packaging/LICENSE
dclab/external/packaging/LICENSE.APACHE
dclab/external/packaging/LICENSE.BSD
dclab/external/packaging/__init__.py
dclab/external/packaging/_structures.py
dclab/external/packaging/version.py
dclab/external/skimage/LICENSE
dclab/external/skimage/__init__.py
dclab/external/skimage/_find_contours.py
dclab/external/skimage/_find_contours_cy.cp310-win_amd64.pyd
dclab/external/skimage/_find_contours_cy.pyx
dclab/external/skimage/_pnpoly.cp310-win_amd64.pyd
dclab/external/skimage/_pnpoly.pyx
dclab/external/skimage/measure.py
dclab/external/skimage/pnpoly.py
dclab/external/skimage/_shared/__init__.py
dclab/external/skimage/_shared/geometry.cp310-win_amd64.pyd
dclab/external/skimage/_shared/geometry.pxd
dclab/external/skimage/_shared/geometry.pyx
dclab/external/statsmodels/LICENSE
dclab/external/statsmodels/__init__.py
dclab/external/statsmodels/nonparametric/__init__.py
dclab/external/statsmodels/nonparametric/_kernel_base.py
dclab/external/statsmodels/nonparametric/kernel_density.py
dclab/external/statsmodels/nonparametric/kernels.py
dclab/features/__init__.py
dclab/features/bright.py
dclab/features/bright_bc.py
dclab/features/bright_perc.py
dclab/features/contour.py
dclab/features/fl_crosstalk.py
dclab/features/inert_ratio.py
dclab/features/volume.py
dclab-2.18.0.dist-info/LICENSE
dclab-2.18.0.dist-info/METADATA
dclab-2.18.0.dist-info/WHEEL
dclab-2.18.0.dist-info/entry_points.txt
dclab-2.18.0.dist-info/top_level.txt
dclab-2.18.0.dist-info/RECORD
