Metadata-Version: 2.1
Name: dclab
Version: 2.18.0
Summary: Library for real-time deformability cytometry (RT-DC)
Author: Benedikt Hartmann, Eoghan O'Connell, Maik Herbig, Maximilian Schlögel, Nadia Sbaa, Paul Müller, Philipp Rosendahl, Raghava Alajangi
Maintainer-email: Paul Müller <dev@craban.de>
License: GPL version 2.0 or later
Project-URL: source, https://github.com/DC-Analysis/dclab
Project-URL: tracker, https://github.com/DC-Analysis/dclab/issues
Project-URL: documentation, https://dclab.readthedocs.io/en/stable/
Project-URL: changelog, https://dclab.readthedocs.io/en/stable/sec_changelog.html
Keywords: RT-DC,deformability,cytometry
Classifier: Operating System :: OS Independent
Classifier: Programming Language :: Python :: 3
Classifier: Topic :: Scientific/Engineering :: Visualization
Classifier: Intended Audience :: Science/Research
Requires-Python: <4,>=3.8
License-File: LICENSE
Requires-Dist: h5py<4,>=3.0.0
Requires-Dist: hdf5plugin<5,>=3.3.1
Requires-Dist: importlib-resources>=6.0
Requires-Dist: numpy<3,>=1.21
Requires-Dist: scipy<2,>=1.10.0
Provides-Extra: all
Requires-Dist: dclab[dcor,export,http,lme4,s3,tdms]; extra == "all"
Provides-Extra: dcor
Requires-Dist: requests<3,>=2.31.0; extra == "dcor"
Provides-Extra: export
Requires-Dist: fcswrite>=0.5.0; extra == "export"
Requires-Dist: imageio[ffmpeg]; extra == "export"
Provides-Extra: http
Requires-Dist: requests<3,>=2.31.0; extra == "http"
Provides-Extra: lme4
Requires-Dist: rpy2>=2.9.4; extra == "lme4"
Provides-Extra: s3
Requires-Dist: boto3>=1.34.31; extra == "s3"
Provides-Extra: tdms
Requires-Dist: imageio[ffmpeg]; extra == "tdms"
Requires-Dist: nptdms<1.9,>=0.23.0; extra == "tdms"
